json_syntax/__init__.py
json_syntax/action_v1.py
json_syntax/attrs.py
json_syntax/cache.py
json_syntax/errors.py
json_syntax/extras/README.md
json_syntax/extras/__init__.py
json_syntax/extras/dynamodb.py
json_syntax/extras/flags.py
json_syntax/extras/loose_dates.py
json_syntax/helpers.py
json_syntax/pattern.py
json_syntax/product.py
json_syntax/ruleset.py
json_syntax/std.py
json_syntax/string.py
json_syntax/types.py
json_syntax/unions.py
json_syntax-2.3.1.dist-info/LICENSE
json_syntax-2.3.1.dist-info/WHEEL
json_syntax-2.3.1.dist-info/METADATA
json_syntax-2.3.1.dist-info/RECORD
