Metadata-Version: 2.1
Name: json-syntax
Version: 2.3.1
Summary: Generates functions to convert Python classes to JSON dumpable objects.
Home-page: https://github.com/UnitedIncome/json-syntax
License: MIT
Author: Ben Samuel
Author-email: bsamuel@unitedincome.com
Requires-Python: >=3.4,<4.0
Classifier: Development Status :: 5 - Production/Stable
Classifier: Intended Audience :: Developers
Classifier: License :: OSI Approved :: MIT License
Classifier: Programming Language :: Python :: 3
Classifier: Programming Language :: Python :: 3.4
Classifier: Programming Language :: Python :: 3.5
Classifier: Programming Language :: Python :: 3.6
Classifier: Programming Language :: Python :: 3.7
Classifier: Programming Language :: Python :: 3.8
Classifier: Topic :: Software Development :: Libraries
Requires-Dist: python-dateutil (>=2.7,<3.0); python_version < "3.7"
Requires-Dist: typing (>=3.7,<4.0); python_version < "3.5"
Project-URL: Repository, https://github.com/UnitedIncome/json-syntax
